{"cameraMode":{"drawMode":0,"name":"Shaded","section":"Shading Mode"},"sceneLighting":false,"audioPlay":false,"sceneViewState":{"m_AlwaysRefresh":false,"showFog":true,"showSkybox":false,"showFlares":true,"showImageEffects":true,"showParticleSystems":true,"showVisualEffectGraphs":true,"m_FxEnabled":true},"in2DMode":false,"pivot":{"x":2.1702027320861818,"y":1.2123825550079346,"z":89.5328598022461},"rotation":{"x":0.14536152780056,"y":0.08300379663705826,"z":-0.012239256873726845,"w":0.9858173131942749},"size":1.6716400384902955,"orthographic":true}